nonebot_plugin_namelist/__init__.py
nonebot_plugin_namelist-0.2.0.dist-info/WHEEL
nonebot_plugin_namelist-0.2.0.dist-info/METADATA
nonebot_plugin_namelist-0.2.0.dist-info/license_files/LICENSE
nonebot_plugin_namelist-0.2.0.dist-info/RECORD
