Metadata-Version: 2.1
Name: nonebot-plugin-namelist
Version: 0.2.0
Summary: Blacklist and whitelist in NoneBot2
License: MIT
Author-email: Akirami <Akiramiaya@outlook.com>
Requires-Python: >=3.8
Requires-Dist: nonebot-adapter-onebot>=2.0.0b1
Requires-Dist: nonebot2>=2.0.0b3
Project-URL: Homepage, https://github.com/A-kirami/nonebot-plugin-namelist
Project-URL: Repository, https://github.com/A-kirami/nonebot-plugin-namelist
